whois/__init__.py
whois/parser.py
whois/time_zones.py
whois/whois.py
whois/data/public_suffix_list.dat
whois_pypi-0.2.dist-info/LICENSE.txt
whois_pypi-0.2.dist-info/METADATA
whois_pypi-0.2.dist-info/WHEEL
whois_pypi-0.2.dist-info/top_level.txt
whois_pypi-0.2.dist-info/RECORD
