Metadata-Version: 2.1
Name: whois-pypi
Version: 0.2
Summary: Whois querying and parsing of domain registration information.
Home-page: https://github.com/Paradoxxs/pywhois
Author: Paradoxxs
Author-email: pypi@adamtilmar.com
License: MIT
Keywords: whois,python
Classifier: Environment :: Web Environment
Classifier: Intended Audience :: Developers
Classifier: License :: OSI Approved :: MIT License
Classifier: Operating System :: OS Independent
Classifier: Programming Language :: Python
Classifier: Topic :: Internet :: WWW/HTTP
Classifier: Programming Language :: Python :: 3
License-File: LICENSE.txt
Requires-Dist: future
Provides-Extra: better_date_conversion
Requires-Dist: python-dateutil ; extra == 'better_date_conversion'
